zipd/__init__.py
zipd/__main__.py
zipd/argparsing.py
zipd/cli.py
zipd/runcommand.py
zipd-0.3.10.dist-info/METADATA
zipd-0.3.10.dist-info/WHEEL
zipd-0.3.10.dist-info/entry_points.txt
zipd-0.3.10.dist-info/licenses/LICENSE
zipd-0.3.10.dist-info/RECORD
