Metadata-Version: 2.3
Name: zipd
Version: 0.3.10
Summary: Recursively zip up a directory/folder
Project-URL: Repository, https://github.com/jmknoble/zipd
Author-email: jmknoble <jmknoble@pobox.com>
License: MIT License
Keywords: cli,git,gitignore,recursive,zip
Classifier: Development Status :: 4 - Beta
Classifier: Environment :: Console
Classifier: Environment :: Other Environment
Classifier: Intended Audience :: Developers
Classifier: Intended Audience :: Information Technology
Classifier: License :: OSI Approved :: MIT License
Classifier: Natural Language :: English
Classifier: Operating System :: OS Independent
Classifier: Programming Language :: Python :: 3
Classifier: Programming Language :: Python :: 3.10
Classifier: Programming Language :: Python :: 3.11
Classifier: Topic :: Utilities
Requires-Python: >=3.10
Requires-Dist: gitignore-parser>=0.0.5
